adcircpy/__init__.py
adcircpy/__main__.py
adcircpy/cmd/__init__.py
adcircpy/cmd/argument_parser.py
adcircpy/cmd/basecmd.py
adcircpy/cmd/best_track_file.py
adcircpy/cmd/best_track_run.py
adcircpy/cmd/diagnose.py
adcircpy/cmd/fort63.py
adcircpy/cmd/iter_smooth.py
adcircpy/cmd/plot_fort61.py
adcircpy/cmd/plot_maxele.py
adcircpy/cmd/plot_mesh.py
adcircpy/cmd/tidal_run.py
adcircpy/cmd/tide_gen.py
adcircpy/driver.py
adcircpy/figures.py
adcircpy/forcing/__init__.py
adcircpy/forcing/base.py
adcircpy/forcing/bctypes.py
adcircpy/forcing/tides/__init__.py
adcircpy/forcing/tides/dataset.py
adcircpy/forcing/tides/hamtide.py
adcircpy/forcing/tides/tides.py
adcircpy/forcing/tides/tpxo.py
adcircpy/forcing/waves/__init__.py
adcircpy/forcing/waves/base.py
adcircpy/forcing/waves/ww3.py
adcircpy/forcing/winds/__init__.py
adcircpy/forcing/winds/_parametric/__init__.py
adcircpy/forcing/winds/_parametric/gao2015.py
adcircpy/forcing/winds/_parametric/holland2010.py
adcircpy/forcing/winds/atmesh.py
adcircpy/forcing/winds/base.py
adcircpy/forcing/winds/best_track.py
adcircpy/forcing/winds/owi.py
adcircpy/fort15.py
adcircpy/mesh/__init__.py
adcircpy/mesh/base.py
adcircpy/mesh/fort13.py
adcircpy/mesh/fort14.py
adcircpy/mesh/mesh.py
adcircpy/mesh/parsers/__init__.py
adcircpy/mesh/parsers/grd.py
adcircpy/mesh/parsers/sms2dm.py
adcircpy/outputs/__init__.py
adcircpy/outputs/base.py
adcircpy/outputs/collection.py
adcircpy/outputs/fort61.py
adcircpy/outputs/fort63.py
adcircpy/outputs/maxele.py
adcircpy/plotting.py
adcircpy/server/__init__.py
adcircpy/server/base_config.py
adcircpy/server/driver_file.py
adcircpy/server/slurm_config.py
adcircpy/server/ssh_config.py
adcircpy/utilities.py
adcircpy-1.2.7.dist-info/entry_points.txt
adcircpy-1.2.7.dist-info/LICENSE
adcircpy-1.2.7.dist-info/WHEEL
adcircpy-1.2.7.dist-info/METADATA
adcircpy-1.2.7.dist-info/RECORD
