Metadata-Version: 2.1
Name: adcircpy
Version: 1.2.7
Summary: Python package for working with ADCIRC input and output files
Home-page: https://github.com/noaa-ocs-modeling/adcircpy.git
License: GPL-3.0-or-later
Author: Zach Burnett
Author-email: zachary.burnett@noaa.gov
Requires-Python: >=3.8,<4.0
Classifier: License :: OSI Approved :: GNU General Public License v3 or later (GPLv3+)
Classifier: Programming Language :: Python :: 3
Classifier: Programming Language :: Python :: 3.10
Classifier: Programming Language :: Python :: 3.8
Classifier: Programming Language :: Python :: 3.9
Provides-Extra: development
Provides-Extra: documentation
Provides-Extra: testing
Requires-Dist: appdirs
Requires-Dist: geopandas (<0.11)
Requires-Dist: haversine
Requires-Dist: isort; extra == "development"
Requires-Dist: m2r2; extra == "documentation"
Requires-Dist: matplotlib
Requires-Dist: netCDF4
Requires-Dist: numpy
Requires-Dist: oitnb; extra == "development"
Requires-Dist: pandas
Requires-Dist: paramiko
Requires-Dist: pooch
Requires-Dist: psutil
Requires-Dist: pyproj (>=2.6)
Requires-Dist: pytest-cov; extra == "testing"
Requires-Dist: pytest-mock; extra == "testing"
Requires-Dist: pytest-socket; extra == "testing"
Requires-Dist: pytest-xdist; extra == "testing"
Requires-Dist: pytest; extra == "testing"
Requires-Dist: requests
Requires-Dist: scipy
Requires-Dist: searvey
Requires-Dist: shapely
Requires-Dist: sphinx-rtd-theme; extra == "documentation"
Requires-Dist: sphinx; extra == "documentation"
Requires-Dist: sphinxcontrib-bibtex; extra == "documentation"
Requires-Dist: sphinxcontrib-programoutput; extra == "documentation"
Requires-Dist: stormevents (>=2.1.3)
Requires-Dist: typepigeon (<2)
Requires-Dist: utm
Project-URL: Documentation, https://adcircpy.readthedocs.io
Project-URL: Repository, https://github.com/noaa-ocs-modeling/adcircpy.git
